{
  "ruleLogicalInfo" : {
    "id" : 5431875,
    "ruleInstanceId" : 0,
    "ruleDesc" : "",
    "execMode" : null,
    "exitCode" : null,
    "folderId" : 5428066,
    "projectId" : 5428057,
    "ruleCode" : "ICE_1622704567891",
    "folderName" : "recon001",
    "folderType" : "RULE",
    "startTime" : null,
    "endTime" : null,
    "ruleName" : "RC012_ORA_SQL_IN",
    "displayName" : null,
    "rulePurpose" : "",
    "ruleTemplate" : null,
    "statusName" : null,
    "ruleCreatedBy" : 5383149,
    "ruleModifiedBy" : 5383149,
    "subjectAreaKey" : 0,
    "ruleStatus" : 1,
    "ruleCreateDate" : "2021-06-03 00:00:00",
    "ruleModifiedDate" : "2021-06-03 00:00:00",
    "enterpriseErrorCode" : "",
    "legalEntityId" : 1,
    "subjectAreaName" : null,
    "execNode" : "",
    "children" : null,
    "objVOList" : [ ],
    "tagVOList" : [ ],
    "ruleFlowList" : null,
    "ruleType" : "Warning",
    "auditExecutedByProcess" : null,
    "auditExecutionMedium" : null,
    "auditExecutionMediumName" : null,
    "comments" : null,
    "successMailUsers" : [ ],
    "failureMailUsers" : [ ],
    "successHeader" : "",
    "failureHeader" : "",
    "failureAttFlag" : 0,
    "successAttFlag" : 0,
    "srcConnId" : 4385955,
    "trgConnId" : 548301,
    "srcSysGroupId" : 0,
    "trgSysGroupId" : 0,
    "srcConn" : "_ORACLE",
    "trgConn" : "SQL_01",
    "elapseTime" : 0,
    "parameterId" : "",
    "type" : null,
    "isRuleExit" : null,
    "ruleCreatedByName" : "shalini.m@toranainc.com",
    "projectName" : "shalini",
    "ruleModifiedByName" : "shalini.m@toranainc.com",
    "ruleClassId" : 5431878,
    "successBody" : "",
    "failureBody" : "",
    "templateId" : 202,
    "templateIdFail" : 202,
    "reportIdList" : [ ],
    "contextInstanceId" : 0,
    "srcConnFlag" : "REGULAR",
    "trgConnFlag" : "REGULAR",
    "degreeOfParallelism" : 0,
    "templateName" : "Rule Template-Default",
    "templateFailureName" : "Rule Template-Default",
    "objExists" : true
  },
  "rulePhysicalInfo" : {
    "objectName" : null,
    "ruleId" : 5431875,
    "reportRuleClassId" : 0,
    "ruleCId" : 0,
    "classVOList" : [ {
      "classId" : 3,
      "name" : null,
      "ruleClassId" : 5431878,
      "connType" : "",
      "execMode" : "recon",
      "index" : 1,
      "classRun" : "com.ice.bpel.CompareData",
      "vid" : "CompareData11",
      "classObjName" : "ICE_1622705332618",
      "queryBuilderXML" : null,
      "connId" : 0,
      "resultType" : "expression",
      "connName" : null,
      "connUrl" : null,
      "connFullUrl" : null,
      "sysGrpId" : 0,
      "ruleId" : 0,
      "ruleName" : null,
      "ruleParameter" : null,
      "srcTrgMaplist" : [ {
        "colMapId" : 5432104,
        "srcColId" : 5432081,
        "trgColId" : 5432100,
        "colMapType" : "join",
        "srcColName" : "state",
        "tgtColName" : "state",
        "colMapExpr" : "state=state",
        "srcTrgColMapVisible" : 1,
        "displayIndex" : 1
      } ],
      "exprlist" : [ {
        "exprID" : 5432105,
        "exprLogID" : 0,
        "exprName" : "EXPR_QGM8IL7",
        "expression" : "S.state == T.state",
        "result" : "Pass",
        "exprType" : "5",
        "exprVisible" : 1,
        "exprIndex" : 1,
        "ruleId" : 5431875,
        "ruleInstanceId" : 0,
        "ruleClassId" : 5431878,
        "ruleName" : null,
        "trueCount" : null,
        "falseCount" : null,
        "errCount" : null,
        "exprOrg" : "S.state == T.state",
        "tc" : null,
        "fc" : null,
        "er" : null,
        "name" : null,
        "ve" : 0,
        "exporg" : null
      } ],
      "paramsVOLst" : [ {
        "ruleClsPropID" : 5431942,
        "paramId" : 531,
        "paramMethod" : "setThresholdExpression",
        "paramValue" : "",
        "srcTrgTbllist" : [ ],
        "fileContent" : null
      }, {
        "ruleClsPropID" : 5431941,
        "paramId" : 530,
        "paramMethod" : "setThresholdFlag",
        "paramValue" : "false",
        "srcTrgTbllist" : null,
        "fileContent" : null
      }, {
        "ruleClsPropID" : 5431940,
        "paramId" : 465,
        "paramMethod" : "setReportXlsx",
        "paramValue" : "No",
        "srcTrgTbllist" : null,
        "fileContent" : null
      }, {
        "ruleClsPropID" : 5431939,
        "paramId" : 73,
        "paramMethod" : "setLoadDataFlag",
        "paramValue" : "No",
        "srcTrgTbllist" : null,
        "fileContent" : null
      }, {
        "ruleClsPropID" : 5431938,
        "paramId" : 72,
        "paramMethod" : "setTimeOut",
        "paramValue" : "",
        "srcTrgTbllist" : null,
        "fileContent" : null
      }, {
        "ruleClsPropID" : 5431937,
        "paramId" : 24,
        "paramMethod" : "setShowErrorData",
        "paramValue" : "No",
        "srcTrgTbllist" : null,
        "fileContent" : null
      }, {
        "ruleClsPropID" : 5431936,
        "paramId" : 23,
        "paramMethod" : "setMaxErrorCount",
        "paramValue" : "500",
        "srcTrgTbllist" : null,
        "fileContent" : null
      }, {
        "ruleClsPropID" : 5431935,
        "paramId" : 22,
        "paramMethod" : "setMaxRowCount",
        "paramValue" : "-1",
        "srcTrgTbllist" : null,
        "fileContent" : null
      }, {
        "ruleClsPropID" : 5431934,
        "paramId" : 798,
        "paramMethod" : "setEngineType",
        "paramValue" : "Null",
        "srcTrgTbllist" : null,
        "fileContent" : null
      }, {
        "ruleClsPropID" : 5431933,
        "paramId" : 10,
        "paramMethod" : "setTargetObject",
        "paramValue" : "GetData21",
        "srcTrgTbllist" : null,
        "fileContent" : null
      }, {
        "ruleClsPropID" : 5431932,
        "paramId" : 9,
        "paramMethod" : "setSourceObject",
        "paramValue" : "GetData11",
        "srcTrgTbllist" : null,
        "fileContent" : null
      } ],
      "bigDataExecMode" : null,
      "srcConnServer" : null,
      "trgConnServer" : null,
      "srcConnExecMode" : null,
      "trgConnExecMode" : null,
      "thresholdFlag" : null,
      "thresholdExpression" : null
    }, {
      "classId" : 1,
      "name" : null,
      "ruleClassId" : 5431877,
      "connType" : "DATABASE",
      "execMode" : "recon",
      "index" : 0,
      "classRun" : "com.ice.bpel.GetData",
      "vid" : "GetData21",
      "classObjName" : "ICE_1622705332618",
      "queryBuilderXML" : null,
      "connId" : 548301,
      "resultType" : "expression",
      "connName" : null,
      "connUrl" : null,
      "connFullUrl" : null,
      "sysGrpId" : 0,
      "ruleId" : 0,
      "ruleName" : null,
      "ruleParameter" : null,
      "srcTrgMaplist" : [ ],
      "exprlist" : [ ],
      "paramsVOLst" : [ {
        "ruleClsPropID" : 5431914,
        "paramId" : 83,
        "paramMethod" : "setColumnsMInfo",
        "paramValue" : "staffid^~^12^~^nvarchar^~^2000^~^1$~$sex^~^1^~^char^~^1^~^2$~$jobcode^~^12^~^nvarchar^~^2000^~^3$~$company^~^12^~^nvarchar^~^2000^~^4$~$salary^~^8^~^float^~^15^~^5$~$bonus^~^2^~^numeric^~^20^~^6$~$comm^~^2^~^numeric^~^20^~^7$~$totalsalary^~^2^~^numeric^~^20^~^8$~$birthd^~^93^~^datetime^~^23^~^9$~$hired^~^93^~^datetime^~^23^~^10$~$lname^~^12^~^nvarchar^~^2000^~^11$~$fname^~^12^~^nvarchar^~^2000^~^12$~$address^~^12^~^nvarchar^~^2000^~^13$~$city^~^12^~^nvarchar^~^2000^~^14$~$state^~^12^~^nvarchar^~^2000^~^15$~$hphone^~^12^~^nvarchar^~^2000^~^16$~$ssn^~^2^~^numeric^~^20^~^17",
        "srcTrgTbllist" : [ ],
        "fileContent" : null
      }, {
        "ruleClsPropID" : 5431913,
        "paramId" : 82,
        "paramMethod" : "setAppendOrderBy",
        "paramValue" : "true",
        "srcTrgTbllist" : null,
        "fileContent" : null
      }, {
        "ruleClsPropID" : 5431911,
        "paramId" : 84,
        "paramMethod" : "setOrderByStr",
        "paramValue" : "15",
        "srcTrgTbllist" : [ ],
        "fileContent" : null
      }, {
        "ruleClsPropID" : 5431910,
        "paramId" : 491,
        "paramMethod" : "setDeferredSort",
        "paramValue" : "false",
        "srcTrgTbllist" : null,
        "fileContent" : null
      }, {
        "ruleClsPropID" : 5431909,
        "paramId" : 337,
        "paramMethod" : "setIsStoredProcedure",
        "paramValue" : "false",
        "srcTrgTbllist" : null,
        "fileContent" : null
      }, {
        "ruleClsPropID" : 5431908,
        "paramId" : 16,
        "paramMethod" : "setConnId",
        "paramValue" : "548301",
        "srcTrgTbllist" : null,
        "fileContent" : null
      }, {
        "ruleClsPropID" : 5431906,
        "paramId" : 6,
        "paramMethod" : "setQueryString",
        "paramValue" : "select * from dbo.STAFF\nWHERE STATE IN('NY','NJ')",
        "srcTrgTbllist" : [ {
          "srcTgtColId" : 5432086,
          "ruleClsPropId" : 5431906,
          "srcTrgColName" : "staffid",
          "srcTrgColDataType" : "nvarchar",
          "colFlagType" : "tgt",
          "srcTrgColVisible" : 0,
          "joinList" : null,
          "mapColName" : null,
          "colFormat" : "",
          "displayIndex" : 0
        }, {
          "srcTgtColId" : 5432087,
          "ruleClsPropId" : 5431906,
          "srcTrgColName" : "sex",
          "srcTrgColDataType" : "char",
          "colFlagType" : "tgt",
          "srcTrgColVisible" : 0,
          "joinList" : null,
          "mapColName" : null,
          "colFormat" : "",
          "displayIndex" : 0
        }, {
          "srcTgtColId" : 5432088,
          "ruleClsPropId" : 5431906,
          "srcTrgColName" : "jobcode",
          "srcTrgColDataType" : "nvarchar",
          "colFlagType" : "tgt",
          "srcTrgColVisible" : 0,
          "joinList" : null,
          "mapColName" : null,
          "colFormat" : "",
          "displayIndex" : 0
        }, {
          "srcTgtColId" : 5432089,
          "ruleClsPropId" : 5431906,
          "srcTrgColName" : "company",
          "srcTrgColDataType" : "nvarchar",
          "colFlagType" : "tgt",
          "srcTrgColVisible" : 0,
          "joinList" : null,
          "mapColName" : null,
          "colFormat" : "",
          "displayIndex" : 0
        }, {
          "srcTgtColId" : 5432090,
          "ruleClsPropId" : 5431906,
          "srcTrgColName" : "salary",
          "srcTrgColDataType" : "float",
          "colFlagType" : "tgt",
          "srcTrgColVisible" : 0,
          "joinList" : null,
          "mapColName" : null,
          "colFormat" : "",
          "displayIndex" : 0
        }, {
          "srcTgtColId" : 5432091,
          "ruleClsPropId" : 5431906,
          "srcTrgColName" : "bonus",
          "srcTrgColDataType" : "numeric",
          "colFlagType" : "tgt",
          "srcTrgColVisible" : 0,
          "joinList" : null,
          "mapColName" : null,
          "colFormat" : "",
          "displayIndex" : 0
        }, {
          "srcTgtColId" : 5432092,
          "ruleClsPropId" : 5431906,
          "srcTrgColName" : "comm",
          "srcTrgColDataType" : "numeric",
          "colFlagType" : "tgt",
          "srcTrgColVisible" : 0,
          "joinList" : null,
          "mapColName" : null,
          "colFormat" : "",
          "displayIndex" : 0
        }, {
          "srcTgtColId" : 5432093,
          "ruleClsPropId" : 5431906,
          "srcTrgColName" : "totalsalary",
          "srcTrgColDataType" : "numeric",
          "colFlagType" : "tgt",
          "srcTrgColVisible" : 0,
          "joinList" : null,
          "mapColName" : null,
          "colFormat" : "",
          "displayIndex" : 0
        }, {
          "srcTgtColId" : 5432094,
          "ruleClsPropId" : 5431906,
          "srcTrgColName" : "birthd",
          "srcTrgColDataType" : "datetime",
          "colFlagType" : "tgt",
          "srcTrgColVisible" : 0,
          "joinList" : null,
          "mapColName" : null,
          "colFormat" : "",
          "displayIndex" : 0
        }, {
          "srcTgtColId" : 5432095,
          "ruleClsPropId" : 5431906,
          "srcTrgColName" : "hired",
          "srcTrgColDataType" : "datetime",
          "colFlagType" : "tgt",
          "srcTrgColVisible" : 0,
          "joinList" : null,
          "mapColName" : null,
          "colFormat" : "",
          "displayIndex" : 0
        }, {
          "srcTgtColId" : 5432096,
          "ruleClsPropId" : 5431906,
          "srcTrgColName" : "lname",
          "srcTrgColDataType" : "nvarchar",
          "colFlagType" : "tgt",
          "srcTrgColVisible" : 0,
          "joinList" : null,
          "mapColName" : null,
          "colFormat" : "",
          "displayIndex" : 0
        }, {
          "srcTgtColId" : 5432097,
          "ruleClsPropId" : 5431906,
          "srcTrgColName" : "fname",
          "srcTrgColDataType" : "nvarchar",
          "colFlagType" : "tgt",
          "srcTrgColVisible" : 0,
          "joinList" : null,
          "mapColName" : null,
          "colFormat" : "",
          "displayIndex" : 0
        }, {
          "srcTgtColId" : 5432098,
          "ruleClsPropId" : 5431906,
          "srcTrgColName" : "address",
          "srcTrgColDataType" : "nvarchar",
          "colFlagType" : "tgt",
          "srcTrgColVisible" : 0,
          "joinList" : null,
          "mapColName" : null,
          "colFormat" : "",
          "displayIndex" : 0
        }, {
          "srcTgtColId" : 5432099,
          "ruleClsPropId" : 5431906,
          "srcTrgColName" : "city",
          "srcTrgColDataType" : "nvarchar",
          "colFlagType" : "tgt",
          "srcTrgColVisible" : 0,
          "joinList" : null,
          "mapColName" : null,
          "colFormat" : "",
          "displayIndex" : 0
        }, {
          "srcTgtColId" : 5432100,
          "ruleClsPropId" : 5431906,
          "srcTrgColName" : "state",
          "srcTrgColDataType" : "nvarchar",
          "colFlagType" : "tgt",
          "srcTrgColVisible" : 0,
          "joinList" : null,
          "mapColName" : null,
          "colFormat" : "",
          "displayIndex" : 0
        }, {
          "srcTgtColId" : 5432101,
          "ruleClsPropId" : 5431906,
          "srcTrgColName" : "hphone",
          "srcTrgColDataType" : "nvarchar",
          "colFlagType" : "tgt",
          "srcTrgColVisible" : 0,
          "joinList" : null,
          "mapColName" : null,
          "colFormat" : "",
          "displayIndex" : 0
        }, {
          "srcTgtColId" : 5432102,
          "ruleClsPropId" : 5431906,
          "srcTrgColName" : "ssn",
          "srcTrgColDataType" : "numeric",
          "colFlagType" : "tgt",
          "srcTrgColVisible" : 0,
          "joinList" : null,
          "mapColName" : null,
          "colFormat" : "",
          "displayIndex" : 0
        } ],
        "fileContent" : null
      } ],
      "bigDataExecMode" : null,
      "srcConnServer" : null,
      "trgConnServer" : null,
      "srcConnExecMode" : null,
      "trgConnExecMode" : null,
      "thresholdFlag" : null,
      "thresholdExpression" : null
    }, {
      "classId" : 1,
      "name" : null,
      "ruleClassId" : 5431876,
      "connType" : "DATABASE",
      "execMode" : "recon",
      "index" : 0,
      "classRun" : "com.ice.bpel.GetData",
      "vid" : "GetData11",
      "classObjName" : "ICE_1622705332618",
      "queryBuilderXML" : null,
      "connId" : 4385955,
      "resultType" : "expression",
      "connName" : null,
      "connUrl" : null,
      "connFullUrl" : null,
      "sysGrpId" : 0,
      "ruleId" : 0,
      "ruleName" : null,
      "ruleParameter" : null,
      "srcTrgMaplist" : [ ],
      "exprlist" : [ ],
      "paramsVOLst" : [ {
        "ruleClsPropID" : 5431888,
        "paramId" : 404,
        "paramMethod" : "setIsMultipleOutVaiables",
        "paramValue" : "false",
        "srcTrgTbllist" : null,
        "fileContent" : null
      }, {
        "ruleClsPropID" : 5431887,
        "paramId" : 83,
        "paramMethod" : "setColumnsMInfo",
        "paramValue" : "staffid^~^12^~^VARCHAR2^~^2000^~^1$~$sex^~^1^~^CHAR^~^1^~^2$~$jobcode^~^12^~^VARCHAR2^~^2000^~^3$~$company^~^12^~^VARCHAR2^~^2000^~^4$~$salary^~^2^~^NUMBER^~^0^~^5$~$bonus^~^2^~^NUMBER^~^20^~^6$~$comm^~^2^~^NUMBER^~^20^~^7$~$totalsalary^~^2^~^NUMBER^~^20^~^8$~$birthd^~^93^~^DATE^~^0^~^9$~$hired^~^93^~^TIMESTAMP^~^0^~^10$~$lname^~^12^~^VARCHAR2^~^2000^~^11$~$fname^~^12^~^VARCHAR2^~^2000^~^12$~$address^~^12^~^VARCHAR2^~^2000^~^13$~$city^~^12^~^VARCHAR2^~^2000^~^14$~$state^~^12^~^VARCHAR2^~^2000^~^15$~$hphone^~^12^~^VARCHAR2^~^2000^~^16$~$ssn^~^2^~^NUMBER^~^20^~^17",
        "srcTrgTbllist" : [ ],
        "fileContent" : null
      }, {
        "ruleClsPropID" : 5431886,
        "paramId" : 82,
        "paramMethod" : "setAppendOrderBy",
        "paramValue" : "true",
        "srcTrgTbllist" : null,
        "fileContent" : null
      }, {
        "ruleClsPropID" : 5431884,
        "paramId" : 84,
        "paramMethod" : "setOrderByStr",
        "paramValue" : "15",
        "srcTrgTbllist" : [ ],
        "fileContent" : null
      }, {
        "ruleClsPropID" : 5431883,
        "paramId" : 491,
        "paramMethod" : "setDeferredSort",
        "paramValue" : "false",
        "srcTrgTbllist" : null,
        "fileContent" : null
      }, {
        "ruleClsPropID" : 5431882,
        "paramId" : 337,
        "paramMethod" : "setIsStoredProcedure",
        "paramValue" : "false",
        "srcTrgTbllist" : null,
        "fileContent" : null
      }, {
        "ruleClsPropID" : 5431881,
        "paramId" : 16,
        "paramMethod" : "setConnId",
        "paramValue" : "4385955",
        "srcTrgTbllist" : null,
        "fileContent" : null
      }, {
        "ruleClsPropID" : 5431879,
        "paramId" : 6,
        "paramMethod" : "setQueryString",
        "paramValue" : "select * from REGRESSION_DATABASE.STAFF\n WHERE STATE IN ('NY ','NJ')",
        "srcTrgTbllist" : [ {
          "srcTgtColId" : 5432067,
          "ruleClsPropId" : 5431879,
          "srcTrgColName" : "staffid",
          "srcTrgColDataType" : "VARCHAR2",
          "colFlagType" : "src",
          "srcTrgColVisible" : 0,
          "joinList" : null,
          "mapColName" : null,
          "colFormat" : "",
          "displayIndex" : 0
        }, {
          "srcTgtColId" : 5432068,
          "ruleClsPropId" : 5431879,
          "srcTrgColName" : "sex",
          "srcTrgColDataType" : "CHAR",
          "colFlagType" : "src",
          "srcTrgColVisible" : 0,
          "joinList" : null,
          "mapColName" : null,
          "colFormat" : "",
          "displayIndex" : 0
        }, {
          "srcTgtColId" : 5432069,
          "ruleClsPropId" : 5431879,
          "srcTrgColName" : "jobcode",
          "srcTrgColDataType" : "VARCHAR2",
          "colFlagType" : "src",
          "srcTrgColVisible" : 0,
          "joinList" : null,
          "mapColName" : null,
          "colFormat" : "",
          "displayIndex" : 0
        }, {
          "srcTgtColId" : 5432070,
          "ruleClsPropId" : 5431879,
          "srcTrgColName" : "company",
          "srcTrgColDataType" : "VARCHAR2",
          "colFlagType" : "src",
          "srcTrgColVisible" : 0,
          "joinList" : null,
          "mapColName" : null,
          "colFormat" : "",
          "displayIndex" : 0
        }, {
          "srcTgtColId" : 5432071,
          "ruleClsPropId" : 5431879,
          "srcTrgColName" : "salary",
          "srcTrgColDataType" : "NUMBER",
          "colFlagType" : "src",
          "srcTrgColVisible" : 0,
          "joinList" : null,
          "mapColName" : null,
          "colFormat" : "",
          "displayIndex" : 0
        }, {
          "srcTgtColId" : 5432072,
          "ruleClsPropId" : 5431879,
          "srcTrgColName" : "bonus",
          "srcTrgColDataType" : "NUMBER",
          "colFlagType" : "src",
          "srcTrgColVisible" : 0,
          "joinList" : null,
          "mapColName" : null,
          "colFormat" : "",
          "displayIndex" : 0
        }, {
          "srcTgtColId" : 5432073,
          "ruleClsPropId" : 5431879,
          "srcTrgColName" : "comm",
          "srcTrgColDataType" : "NUMBER",
          "colFlagType" : "src",
          "srcTrgColVisible" : 0,
          "joinList" : null,
          "mapColName" : null,
          "colFormat" : "",
          "displayIndex" : 0
        }, {
          "srcTgtColId" : 5432074,
          "ruleClsPropId" : 5431879,
          "srcTrgColName" : "totalsalary",
          "srcTrgColDataType" : "NUMBER",
          "colFlagType" : "src",
          "srcTrgColVisible" : 0,
          "joinList" : null,
          "mapColName" : null,
          "colFormat" : "",
          "displayIndex" : 0
        }, {
          "srcTgtColId" : 5432075,
          "ruleClsPropId" : 5431879,
          "srcTrgColName" : "birthd",
          "srcTrgColDataType" : "DATE",
          "colFlagType" : "src",
          "srcTrgColVisible" : 0,
          "joinList" : null,
          "mapColName" : null,
          "colFormat" : "",
          "displayIndex" : 0
        }, {
          "srcTgtColId" : 5432076,
          "ruleClsPropId" : 5431879,
          "srcTrgColName" : "hired",
          "srcTrgColDataType" : "TIMESTAMP",
          "colFlagType" : "src",
          "srcTrgColVisible" : 0,
          "joinList" : null,
          "mapColName" : null,
          "colFormat" : "",
          "displayIndex" : 0
        }, {
          "srcTgtColId" : 5432077,
          "ruleClsPropId" : 5431879,
          "srcTrgColName" : "lname",
          "srcTrgColDataType" : "VARCHAR2",
          "colFlagType" : "src",
          "srcTrgColVisible" : 0,
          "joinList" : null,
          "mapColName" : null,
          "colFormat" : "",
          "displayIndex" : 0
        }, {
          "srcTgtColId" : 5432078,
          "ruleClsPropId" : 5431879,
          "srcTrgColName" : "fname",
          "srcTrgColDataType" : "VARCHAR2",
          "colFlagType" : "src",
          "srcTrgColVisible" : 0,
          "joinList" : null,
          "mapColName" : null,
          "colFormat" : "",
          "displayIndex" : 0
        }, {
          "srcTgtColId" : 5432079,
          "ruleClsPropId" : 5431879,
          "srcTrgColName" : "address",
          "srcTrgColDataType" : "VARCHAR2",
          "colFlagType" : "src",
          "srcTrgColVisible" : 0,
          "joinList" : null,
          "mapColName" : null,
          "colFormat" : "",
          "displayIndex" : 0
        }, {
          "srcTgtColId" : 5432080,
          "ruleClsPropId" : 5431879,
          "srcTrgColName" : "city",
          "srcTrgColDataType" : "VARCHAR2",
          "colFlagType" : "src",
          "srcTrgColVisible" : 0,
          "joinList" : null,
          "mapColName" : null,
          "colFormat" : "",
          "displayIndex" : 0
        }, {
          "srcTgtColId" : 5432081,
          "ruleClsPropId" : 5431879,
          "srcTrgColName" : "state",
          "srcTrgColDataType" : "VARCHAR2",
          "colFlagType" : "src",
          "srcTrgColVisible" : 0,
          "joinList" : null,
          "mapColName" : null,
          "colFormat" : "",
          "displayIndex" : 0
        }, {
          "srcTgtColId" : 5432082,
          "ruleClsPropId" : 5431879,
          "srcTrgColName" : "hphone",
          "srcTrgColDataType" : "VARCHAR2",
          "colFlagType" : "src",
          "srcTrgColVisible" : 0,
          "joinList" : null,
          "mapColName" : null,
          "colFormat" : "",
          "displayIndex" : 0
        }, {
          "srcTgtColId" : 5432083,
          "ruleClsPropId" : 5431879,
          "srcTrgColName" : "ssn",
          "srcTrgColDataType" : "NUMBER",
          "colFlagType" : "src",
          "srcTrgColVisible" : 0,
          "joinList" : null,
          "mapColName" : null,
          "colFormat" : "",
          "displayIndex" : 0
        } ],
        "fileContent" : null
      } ],
      "bigDataExecMode" : null,
      "srcConnServer" : null,
      "trgConnServer" : null,
      "srcConnExecMode" : null,
      "trgConnExecMode" : null,
      "thresholdFlag" : null,
      "thresholdExpression" : null
    } ],
    "srcTrgTbllist" : [ {
      "srcTgtColId" : 5432067,
      "ruleClsPropId" : 5431879,
      "srcTrgColName" : "staffid",
      "srcTrgColDataType" : "VARCHAR2",
      "colFlagType" : "src",
      "srcTrgColVisible" : 0,
      "joinList" : null,
      "mapColName" : "staffid",
      "colFormat" : "",
      "displayIndex" : 0
    }, {
      "srcTgtColId" : 5432068,
      "ruleClsPropId" : 5431879,
      "srcTrgColName" : "sex",
      "srcTrgColDataType" : "CHAR",
      "colFlagType" : "src",
      "srcTrgColVisible" : 0,
      "joinList" : null,
      "mapColName" : "sex",
      "colFormat" : "",
      "displayIndex" : 0
    }, {
      "srcTgtColId" : 5432069,
      "ruleClsPropId" : 5431879,
      "srcTrgColName" : "jobcode",
      "srcTrgColDataType" : "VARCHAR2",
      "colFlagType" : "src",
      "srcTrgColVisible" : 0,
      "joinList" : null,
      "mapColName" : "jobcode",
      "colFormat" : "",
      "displayIndex" : 0
    }, {
      "srcTgtColId" : 5432070,
      "ruleClsPropId" : 5431879,
      "srcTrgColName" : "company",
      "srcTrgColDataType" : "VARCHAR2",
      "colFlagType" : "src",
      "srcTrgColVisible" : 0,
      "joinList" : null,
      "mapColName" : "company",
      "colFormat" : "",
      "displayIndex" : 0
    }, {
      "srcTgtColId" : 5432071,
      "ruleClsPropId" : 5431879,
      "srcTrgColName" : "salary",
      "srcTrgColDataType" : "NUMBER",
      "colFlagType" : "src",
      "srcTrgColVisible" : 0,
      "joinList" : null,
      "mapColName" : "salary",
      "colFormat" : "",
      "displayIndex" : 0
    }, {
      "srcTgtColId" : 5432072,
      "ruleClsPropId" : 5431879,
      "srcTrgColName" : "bonus",
      "srcTrgColDataType" : "NUMBER",
      "colFlagType" : "src",
      "srcTrgColVisible" : 0,
      "joinList" : null,
      "mapColName" : "bonus",
      "colFormat" : "",
      "displayIndex" : 0
    }, {
      "srcTgtColId" : 5432073,
      "ruleClsPropId" : 5431879,
      "srcTrgColName" : "comm",
      "srcTrgColDataType" : "NUMBER",
      "colFlagType" : "src",
      "srcTrgColVisible" : 0,
      "joinList" : null,
      "mapColName" : "comm",
      "colFormat" : "",
      "displayIndex" : 0
    }, {
      "srcTgtColId" : 5432074,
      "ruleClsPropId" : 5431879,
      "srcTrgColName" : "totalsalary",
      "srcTrgColDataType" : "NUMBER",
      "colFlagType" : "src",
      "srcTrgColVisible" : 0,
      "joinList" : null,
      "mapColName" : "totalsalary",
      "colFormat" : "",
      "displayIndex" : 0
    }, {
      "srcTgtColId" : 5432075,
      "ruleClsPropId" : 5431879,
      "srcTrgColName" : "birthd",
      "srcTrgColDataType" : "DATE",
      "colFlagType" : "src",
      "srcTrgColVisible" : 0,
      "joinList" : null,
      "mapColName" : "birthd",
      "colFormat" : "",
      "displayIndex" : 0
    }, {
      "srcTgtColId" : 5432076,
      "ruleClsPropId" : 5431879,
      "srcTrgColName" : "hired",
      "srcTrgColDataType" : "TIMESTAMP",
      "colFlagType" : "src",
      "srcTrgColVisible" : 0,
      "joinList" : null,
      "mapColName" : "hired",
      "colFormat" : "",
      "displayIndex" : 0
    }, {
      "srcTgtColId" : 5432077,
      "ruleClsPropId" : 5431879,
      "srcTrgColName" : "lname",
      "srcTrgColDataType" : "VARCHAR2",
      "colFlagType" : "src",
      "srcTrgColVisible" : 0,
      "joinList" : null,
      "mapColName" : "lname",
      "colFormat" : "",
      "displayIndex" : 0
    }, {
      "srcTgtColId" : 5432078,
      "ruleClsPropId" : 5431879,
      "srcTrgColName" : "fname",
      "srcTrgColDataType" : "VARCHAR2",
      "colFlagType" : "src",
      "srcTrgColVisible" : 0,
      "joinList" : null,
      "mapColName" : "fname",
      "colFormat" : "",
      "displayIndex" : 0
    }, {
      "srcTgtColId" : 5432079,
      "ruleClsPropId" : 5431879,
      "srcTrgColName" : "address",
      "srcTrgColDataType" : "VARCHAR2",
      "colFlagType" : "src",
      "srcTrgColVisible" : 0,
      "joinList" : null,
      "mapColName" : "address",
      "colFormat" : "",
      "displayIndex" : 0
    }, {
      "srcTgtColId" : 5432080,
      "ruleClsPropId" : 5431879,
      "srcTrgColName" : "city",
      "srcTrgColDataType" : "VARCHAR2",
      "colFlagType" : "src",
      "srcTrgColVisible" : 0,
      "joinList" : null,
      "mapColName" : "city",
      "colFormat" : "",
      "displayIndex" : 0
    }, {
      "srcTgtColId" : 5432081,
      "ruleClsPropId" : 5431879,
      "srcTrgColName" : "state",
      "srcTrgColDataType" : "VARCHAR2",
      "colFlagType" : "src",
      "srcTrgColVisible" : 0,
      "joinList" : null,
      "mapColName" : "state",
      "colFormat" : "",
      "displayIndex" : 0
    }, {
      "srcTgtColId" : 5432082,
      "ruleClsPropId" : 5431879,
      "srcTrgColName" : "hphone",
      "srcTrgColDataType" : "VARCHAR2",
      "colFlagType" : "src",
      "srcTrgColVisible" : 0,
      "joinList" : null,
      "mapColName" : "hphone",
      "colFormat" : "",
      "displayIndex" : 0
    }, {
      "srcTgtColId" : 5432083,
      "ruleClsPropId" : 5431879,
      "srcTrgColName" : "ssn",
      "srcTrgColDataType" : "NUMBER",
      "colFlagType" : "src",
      "srcTrgColVisible" : 0,
      "joinList" : null,
      "mapColName" : "ssn",
      "colFormat" : "",
      "displayIndex" : 0
    }, {
      "srcTgtColId" : 5432086,
      "ruleClsPropId" : 5431906,
      "srcTrgColName" : "staffid",
      "srcTrgColDataType" : "nvarchar",
      "colFlagType" : "tgt",
      "srcTrgColVisible" : 0,
      "joinList" : null,
      "mapColName" : "staffid",
      "colFormat" : "",
      "displayIndex" : 0
    }, {
      "srcTgtColId" : 5432087,
      "ruleClsPropId" : 5431906,
      "srcTrgColName" : "sex",
      "srcTrgColDataType" : "char",
      "colFlagType" : "tgt",
      "srcTrgColVisible" : 0,
      "joinList" : null,
      "mapColName" : "sex",
      "colFormat" : "",
      "displayIndex" : 0
    }, {
      "srcTgtColId" : 5432088,
      "ruleClsPropId" : 5431906,
      "srcTrgColName" : "jobcode",
      "srcTrgColDataType" : "nvarchar",
      "colFlagType" : "tgt",
      "srcTrgColVisible" : 0,
      "joinList" : null,
      "mapColName" : "jobcode",
      "colFormat" : "",
      "displayIndex" : 0
    }, {
      "srcTgtColId" : 5432089,
      "ruleClsPropId" : 5431906,
      "srcTrgColName" : "company",
      "srcTrgColDataType" : "nvarchar",
      "colFlagType" : "tgt",
      "srcTrgColVisible" : 0,
      "joinList" : null,
      "mapColName" : "company",
      "colFormat" : "",
      "displayIndex" : 0
    }, {
      "srcTgtColId" : 5432090,
      "ruleClsPropId" : 5431906,
      "srcTrgColName" : "salary",
      "srcTrgColDataType" : "float",
      "colFlagType" : "tgt",
      "srcTrgColVisible" : 0,
      "joinList" : null,
      "mapColName" : "salary",
      "colFormat" : "",
      "displayIndex" : 0
    }, {
      "srcTgtColId" : 5432091,
      "ruleClsPropId" : 5431906,
      "srcTrgColName" : "bonus",
      "srcTrgColDataType" : "numeric",
      "colFlagType" : "tgt",
      "srcTrgColVisible" : 0,
      "joinList" : null,
      "mapColName" : "bonus",
      "colFormat" : "",
      "displayIndex" : 0
    }, {
      "srcTgtColId" : 5432092,
      "ruleClsPropId" : 5431906,
      "srcTrgColName" : "comm",
      "srcTrgColDataType" : "numeric",
      "colFlagType" : "tgt",
      "srcTrgColVisible" : 0,
      "joinList" : null,
      "mapColName" : "comm",
      "colFormat" : "",
      "displayIndex" : 0
    }, {
      "srcTgtColId" : 5432093,
      "ruleClsPropId" : 5431906,
      "srcTrgColName" : "totalsalary",
      "srcTrgColDataType" : "numeric",
      "colFlagType" : "tgt",
      "srcTrgColVisible" : 0,
      "joinList" : null,
      "mapColName" : "totalsalary",
      "colFormat" : "",
      "displayIndex" : 0
    }, {
      "srcTgtColId" : 5432094,
      "ruleClsPropId" : 5431906,
      "srcTrgColName" : "birthd",
      "srcTrgColDataType" : "datetime",
      "colFlagType" : "tgt",
      "srcTrgColVisible" : 0,
      "joinList" : null,
      "mapColName" : "birthd",
      "colFormat" : "",
      "displayIndex" : 0
    }, {
      "srcTgtColId" : 5432095,
      "ruleClsPropId" : 5431906,
      "srcTrgColName" : "hired",
      "srcTrgColDataType" : "datetime",
      "colFlagType" : "tgt",
      "srcTrgColVisible" : 0,
      "joinList" : null,
      "mapColName" : "hired",
      "colFormat" : "",
      "displayIndex" : 0
    }, {
      "srcTgtColId" : 5432096,
      "ruleClsPropId" : 5431906,
      "srcTrgColName" : "lname",
      "srcTrgColDataType" : "nvarchar",
      "colFlagType" : "tgt",
      "srcTrgColVisible" : 0,
      "joinList" : null,
      "mapColName" : "lname",
      "colFormat" : "",
      "displayIndex" : 0
    }, {
      "srcTgtColId" : 5432097,
      "ruleClsPropId" : 5431906,
      "srcTrgColName" : "fname",
      "srcTrgColDataType" : "nvarchar",
      "colFlagType" : "tgt",
      "srcTrgColVisible" : 0,
      "joinList" : null,
      "mapColName" : "fname",
      "colFormat" : "",
      "displayIndex" : 0
    }, {
      "srcTgtColId" : 5432098,
      "ruleClsPropId" : 5431906,
      "srcTrgColName" : "address",
      "srcTrgColDataType" : "nvarchar",
      "colFlagType" : "tgt",
      "srcTrgColVisible" : 0,
      "joinList" : null,
      "mapColName" : "address",
      "colFormat" : "",
      "displayIndex" : 0
    }, {
      "srcTgtColId" : 5432099,
      "ruleClsPropId" : 5431906,
      "srcTrgColName" : "city",
      "srcTrgColDataType" : "nvarchar",
      "colFlagType" : "tgt",
      "srcTrgColVisible" : 0,
      "joinList" : null,
      "mapColName" : "city",
      "colFormat" : "",
      "displayIndex" : 0
    }, {
      "srcTgtColId" : 5432100,
      "ruleClsPropId" : 5431906,
      "srcTrgColName" : "state",
      "srcTrgColDataType" : "nvarchar",
      "colFlagType" : "tgt",
      "srcTrgColVisible" : 0,
      "joinList" : null,
      "mapColName" : "state",
      "colFormat" : "",
      "displayIndex" : 0
    }, {
      "srcTgtColId" : 5432101,
      "ruleClsPropId" : 5431906,
      "srcTrgColName" : "hphone",
      "srcTrgColDataType" : "nvarchar",
      "colFlagType" : "tgt",
      "srcTrgColVisible" : 0,
      "joinList" : null,
      "mapColName" : "hphone",
      "colFormat" : "",
      "displayIndex" : 0
    }, {
      "srcTgtColId" : 5432102,
      "ruleClsPropId" : 5431906,
      "srcTrgColName" : "ssn",
      "srcTrgColDataType" : "numeric",
      "colFlagType" : "tgt",
      "srcTrgColVisible" : 0,
      "joinList" : null,
      "mapColName" : "ssn",
      "colFormat" : "",
      "displayIndex" : 0
    } ],
    "colMapList" : [ {
      "colMapId" : 5432104,
      "srcColId" : 5432081,
      "trgColId" : 5432100,
      "colMapType" : "join",
      "srcColName" : "state",
      "tgtColName" : "state",
      "colMapExpr" : "state=state",
      "srcTrgColMapVisible" : 1,
      "displayIndex" : 1
    } ],
    "objectVOList" : null,
    "srcCount" : null,
    "trgCount" : null,
    "srcMissing" : null,
    "trgMissing" : null,
    "commonRows" : null,
    "classResult" : null,
    "classStatus" : null,
    "resultType" : null,
    "showErrorData" : null,
    "reportXlsx" : null,
    "ruleParameter" : "",
    "classCreatedBy" : 0,
    "classModifydBy" : 0,
    "classCreateDate" : null,
    "classModifyDate" : null,
    "exprVOList" : [ {
      "exprID" : 5432105,
      "exprLogID" : 0,
      "exprName" : "EXPR_QGM8IL7",
      "expression" : "S.state == T.state",
      "result" : "Pass",
      "exprType" : "5",
      "exprVisible" : 1,
      "exprIndex" : 1,
      "ruleId" : 5431875,
      "ruleInstanceId" : 0,
      "ruleClassId" : 5431878,
      "ruleName" : null,
      "trueCount" : null,
      "falseCount" : null,
      "errCount" : null,
      "exprOrg" : null,
      "tc" : null,
      "fc" : null,
      "er" : null,
      "name" : null,
      "ve" : 0,
      "exporg" : null
    } ]
  }
}