{
  "ruleLogicalInfo" : {
    "id" : 2266165,
    "ruleInstanceId" : 0,
    "ruleDesc" : "",
    "execMode" : "recon",
    "exitCode" : null,
    "folderId" : 2266085,
    "projectId" : 2266058,
    "ruleCode" : "ICE_1583491810684",
    "folderName" : "RECON-SQLN",
    "folderType" : "RULE",
    "startTime" : null,
    "endTime" : null,
    "ruleName" : "R001-Rule with Default query by selecting view from schema",
    "displayName" : null,
    "rulePurpose" : "",
    "ruleTemplate" : null,
    "statusName" : null,
    "ruleCreatedBy" : 7,
    "ruleModifiedBy" : 7,
    "subjectAreaKey" : 0,
    "ruleStatus" : 1,
    "ruleCreateDate" : "2020-03-06 00:00:00",
    "ruleModifiedDate" : "2022-05-17 00:00:00",
    "enterpriseErrorCode" : "",
    "legalEntityId" : 1,
    "subjectAreaName" : null,
    "execNode" : "",
    "children" : null,
    "objVOList" : [ ],
    "tagVOList" : [ ],
    "ruleFlowList" : null,
    "ruleType" : "Warning",
    "auditExecutedByProcess" : null,
    "auditExecutionMedium" : null,
    "auditExecutionMediumName" : null,
    "comments" : null,
    "successMailUsers" : [ ],
    "failureMailUsers" : [ ],
    "successHeader" : "",
    "failureHeader" : "",
    "failureAttFlag" : 0,
    "successAttFlag" : 0,
    "srcConnId" : 2452,
    "trgConnId" : 2452,
    "srcSysGroupId" : 0,
    "trgSysGroupId" : 0,
    "srcConn" : "SQLSERVERNATIVE_SqlAuth",
    "trgConn" : "SQLSERVERNATIVE_SqlAuth",
    "elapseTime" : 0,
    "parameterId" : "",
    "type" : null,
    "isRuleExit" : null,
    "ruleCreatedByName" : "admin",
    "projectName" : "16.2.0_Pallavi",
    "ruleModifiedByName" : "admin",
    "ruleClassId" : 2266168,
    "successBody" : "",
    "failureBody" : "",
    "templateId" : 203,
    "templateIdFail" : 203,
    "reportIdList" : [ ],
    "contextInstanceId" : 0,
    "srcConnFlag" : "REGULAR",
    "trgConnFlag" : "REGULAR",
    "degreeOfParallelism" : 0,
    "templateName" : "Rule Template-Default",
    "templateFailureName" : "Rule Template-Default",
    "objExists" : true
  },
  "rulePhysicalInfo" : {
    "objectName" : null,
    "ruleId" : 2266165,
    "reportRuleClassId" : 0,
    "ruleCId" : 0,
    "classVOList" : [ {
      "classId" : 3,
      "name" : null,
      "ruleClassId" : 2266168,
      "connType" : "",
      "execMode" : "recon",
      "index" : 1,
      "classRun" : "com.ice.bpel.CompareData",
      "vid" : "CompareData11",
      "classObjName" : "ICE_1583492008527",
      "queryBuilderXML" : null,
      "connId" : 0,
      "resultType" : "a-b,b-a",
      "connName" : null,
      "connUrl" : null,
      "connFullUrl" : null,
      "sysGrpId" : 0,
      "ruleId" : 0,
      "ruleName" : null,
      "ruleParameter" : null,
      "srcTrgMaplist" : [ {
        "colMapId" : 10548162,
        "srcColId" : 10548129,
        "trgColId" : 10548146,
        "colMapType" : "join",
        "srcColName" : "flag_type",
        "tgtColName" : "flag_type",
        "colMapExpr" : "flag_type=flag_type",
        "srcTrgColMapVisible" : 1,
        "displayIndex" : 30
      } ],
      "exprlist" : [ {
        "exprID" : 2266226,
        "exprLogID" : 0,
        "exprName" : "audit_executed_from",
        "expression" : "S.audit_executed_from == T.audit_executed_from",
        "result" : "Pass",
        "exprType" : "5",
        "exprVisible" : 1,
        "exprIndex" : 29,
        "ruleId" : 2266165,
        "ruleInstanceId" : 0,
        "ruleClassId" : 2266168,
        "ruleName" : null,
        "trueCount" : null,
        "falseCount" : null,
        "errCount" : null,
        "exprOrg" : "S.audit_executed_from == T.audit_executed_from",
        "tc" : null,
        "fc" : null,
        "er" : null,
        "name" : null,
        "ve" : 0,
        "exporg" : null
      } ],
      "derivedexprlist" : null,
      "paramsVOLst" : [ {
        "ruleClsPropID" : 2266213,
        "paramId" : 9,
        "paramMethod" : "setSourceObject",
        "paramValue" : "GetData11",
        "srcTrgTbllist" : null,
        "fileContent" : null
      }, {
        "ruleClsPropID" : 2266214,
        "paramId" : 10,
        "paramMethod" : "setTargetObject",
        "paramValue" : "GetData21",
        "srcTrgTbllist" : null,
        "fileContent" : null
      }, {
        "ruleClsPropID" : 2266215,
        "paramId" : 22,
        "paramMethod" : "setMaxRowCount",
        "paramValue" : "-1",
        "srcTrgTbllist" : null,
        "fileContent" : null
      }, {
        "ruleClsPropID" : 2266216,
        "paramId" : 23,
        "paramMethod" : "setMaxErrorCount",
        "paramValue" : "500",
        "srcTrgTbllist" : null,
        "fileContent" : null
      }, {
        "ruleClsPropID" : 2266217,
        "paramId" : 24,
        "paramMethod" : "setShowErrorData",
        "paramValue" : "Yes",
        "srcTrgTbllist" : null,
        "fileContent" : null
      }, {
        "ruleClsPropID" : 2266218,
        "paramId" : 72,
        "paramMethod" : "setTimeOut",
        "paramValue" : "",
        "srcTrgTbllist" : null,
        "fileContent" : null
      }, {
        "ruleClsPropID" : 2266219,
        "paramId" : 73,
        "paramMethod" : "setLoadDataFlag",
        "paramValue" : "No",
        "srcTrgTbllist" : null,
        "fileContent" : null
      }, {
        "ruleClsPropID" : 2266221,
        "paramId" : 465,
        "paramMethod" : "setReportXlsx",
        "paramValue" : "No",
        "srcTrgTbllist" : null,
        "fileContent" : null
      }, {
        "ruleClsPropID" : 2266222,
        "paramId" : 530,
        "paramMethod" : "setThresholdFlag",
        "paramValue" : "false",
        "srcTrgTbllist" : null,
        "fileContent" : null
      }, {
        "ruleClsPropID" : 2266223,
        "paramId" : 531,
        "paramMethod" : "setThresholdExpression",
        "paramValue" : "",
        "srcTrgTbllist" : [ ],
        "fileContent" : null
      }, {
        "ruleClsPropID" : 10548160,
        "paramId" : 798,
        "paramMethod" : "setEngineType",
        "paramValue" : "Null",
        "srcTrgTbllist" : null,
        "fileContent" : null
      } ],
      "bigDataExecMode" : null,
      "srcConnServer" : null,
      "trgConnServer" : null,
      "srcConnExecMode" : null,
      "trgConnExecMode" : null,
      "thresholdFlag" : null,
      "thresholdExpression" : null
    }, {
      "classId" : 1,
      "name" : null,
      "ruleClassId" : 2266166,
      "connType" : "DATABASE",
      "execMode" : "recon",
      "index" : 0,
      "classRun" : "com.ice.bpel.GetData",
      "vid" : "GetData11",
      "classObjName" : "ICE_1583492008527",
      "queryBuilderXML" : null,
      "connId" : 2452,
      "resultType" : "a-b,b-a",
      "connName" : null,
      "connUrl" : null,
      "connFullUrl" : null,
      "sysGrpId" : 0,
      "ruleId" : 0,
      "ruleName" : null,
      "ruleParameter" : null,
      "srcTrgMaplist" : [ ],
      "exprlist" : [ ],
      "derivedexprlist" : null,
      "paramsVOLst" : [ {
        "ruleClsPropID" : 2266169,
        "paramId" : 6,
        "paramMethod" : "setQueryString",
        "paramValue" : "select * from DBO.ICE_IQA_INFO_VIEW",
        "srcTrgTbllist" : [ {
          "srcTgtColId" : 10548129,
          "ruleClsPropId" : 2266169,
          "srcTrgColName" : "flag_type",
          "srcTrgColDataType" : "varchar",
          "colFlagType" : "src",
          "srcTrgColVisible" : 1,
          "joinList" : null,
          "mapColName" : null,
          "colFormat" : "",
          "displayIndex" : 1
        }, {
          "srcTgtColId" : 10548130,
          "ruleClsPropId" : 2266169,
          "srcTrgColName" : "req_id",
          "srcTrgColDataType" : "int",
          "colFlagType" : "src",
          "srcTrgColVisible" : 1,
          "joinList" : null,
          "mapColName" : null,
          "colFormat" : "",
          "displayIndex" : 2
        }, {
          "srcTgtColId" : 10548131,
          "ruleClsPropId" : 2266169,
          "srcTrgColName" : "req_code",
          "srcTrgColDataType" : "varchar",
          "colFlagType" : "src",
          "srcTrgColVisible" : 1,
          "joinList" : null,
          "mapColName" : null,
          "colFormat" : "",
          "displayIndex" : 3
        }, {
          "srcTgtColId" : 10548132,
          "ruleClsPropId" : 2266169,
          "srcTrgColName" : "project_name",
          "srcTrgColDataType" : "varchar",
          "colFlagType" : "src",
          "srcTrgColVisible" : 1,
          "joinList" : null,
          "mapColName" : null,
          "colFormat" : "",
          "displayIndex" : 4
        }, {
          "srcTgtColId" : 10548133,
          "ruleClsPropId" : 2266169,
          "srcTrgColName" : "folder_name",
          "srcTrgColDataType" : "varchar",
          "colFlagType" : "src",
          "srcTrgColVisible" : 1,
          "joinList" : null,
          "mapColName" : null,
          "colFormat" : "",
          "displayIndex" : 5
        }, {
          "srcTgtColId" : 10548134,
          "ruleClsPropId" : 2266169,
          "srcTrgColName" : "req_name",
          "srcTrgColDataType" : "varchar",
          "colFlagType" : "src",
          "srcTrgColVisible" : 1,
          "joinList" : null,
          "mapColName" : null,
          "colFormat" : "",
          "displayIndex" : 6
        }, {
          "srcTgtColId" : 10548135,
          "ruleClsPropId" : 2266169,
          "srcTrgColName" : "req_desc",
          "srcTrgColDataType" : "varchar",
          "colFlagType" : "src",
          "srcTrgColVisible" : 1,
          "joinList" : null,
          "mapColName" : null,
          "colFormat" : "",
          "displayIndex" : 7
        }, {
          "srcTgtColId" : 10548136,
          "ruleClsPropId" : 2266169,
          "srcTrgColName" : "audit_exit_code",
          "srcTrgColDataType" : "float",
          "colFlagType" : "src",
          "srcTrgColVisible" : 1,
          "joinList" : null,
          "mapColName" : null,
          "colFormat" : "",
          "displayIndex" : 8
        }, {
          "srcTgtColId" : 10548137,
          "ruleClsPropId" : 2266169,
          "srcTrgColName" : "audit_execution_started_at",
          "srcTrgColDataType" : "datetime",
          "colFlagType" : "src",
          "srcTrgColVisible" : 1,
          "joinList" : null,
          "mapColName" : null,
          "colFormat" : "",
          "displayIndex" : 9
        }, {
          "srcTgtColId" : 10548138,
          "ruleClsPropId" : 2266169,
          "srcTrgColName" : "audit_execution_completed_at",
          "srcTrgColDataType" : "datetime",
          "colFlagType" : "src",
          "srcTrgColVisible" : 1,
          "joinList" : null,
          "mapColName" : null,
          "colFormat" : "",
          "displayIndex" : 10
        }, {
          "srcTgtColId" : 10548139,
          "ruleClsPropId" : 2266169,
          "srcTrgColName" : "audit_executed_from",
          "srcTrgColDataType" : "varchar",
          "colFlagType" : "src",
          "srcTrgColVisible" : 1,
          "joinList" : null,
          "mapColName" : null,
          "colFormat" : "",
          "displayIndex" : 11
        }, {
          "srcTgtColId" : 10548140,
          "ruleClsPropId" : 2266169,
          "srcTrgColName" : "context_type",
          "srcTrgColDataType" : "varchar",
          "colFlagType" : "src",
          "srcTrgColVisible" : 1,
          "joinList" : null,
          "mapColName" : null,
          "colFormat" : "",
          "displayIndex" : 12
        }, {
          "srcTgtColId" : 10548141,
          "ruleClsPropId" : 2266169,
          "srcTrgColName" : "executed_by",
          "srcTrgColDataType" : "varchar",
          "colFlagType" : "src",
          "srcTrgColVisible" : 1,
          "joinList" : null,
          "mapColName" : null,
          "colFormat" : "",
          "displayIndex" : 13
        }, {
          "srcTgtColId" : 10548142,
          "ruleClsPropId" : 2266169,
          "srcTrgColName" : "audit_status",
          "srcTrgColDataType" : "varchar",
          "colFlagType" : "src",
          "srcTrgColVisible" : 1,
          "joinList" : null,
          "mapColName" : null,
          "colFormat" : "",
          "displayIndex" : 14
        } ],
        "fileContent" : null
      }, {
        "ruleClsPropID" : 2266171,
        "paramId" : 16,
        "paramMethod" : "setConnId",
        "paramValue" : "2452",
        "srcTrgTbllist" : null,
        "fileContent" : null
      }, {
        "ruleClsPropID" : 2266172,
        "paramId" : 337,
        "paramMethod" : "setIsStoredProcedure",
        "paramValue" : "false",
        "srcTrgTbllist" : null,
        "fileContent" : null
      }, {
        "ruleClsPropID" : 2266173,
        "paramId" : 84,
        "paramMethod" : "setOrderByStr",
        "paramValue" : "1",
        "srcTrgTbllist" : [ ],
        "fileContent" : null
      }, {
        "ruleClsPropID" : 2266175,
        "paramId" : 82,
        "paramMethod" : "setAppendOrderBy",
        "paramValue" : "true",
        "srcTrgTbllist" : null,
        "fileContent" : null
      }, {
        "ruleClsPropID" : 2266176,
        "paramId" : 83,
        "paramMethod" : "setColumnsMInfo",
        "paramValue" : "flag_type^~^12^~^varchar^~^11^~^1$~$req_id^~^4^~^int^~^10^~^2$~$req_code^~^12^~^varchar^~^50^~^3$~$project_name^~^12^~^varchar^~^100^~^4$~$folder_name^~^12^~^varchar^~^50^~^5$~$req_name^~^12^~^varchar^~^2000^~^6$~$req_desc^~^12^~^varchar^~^4000^~^7$~$audit_exit_code^~^8^~^float^~^15^~^8$~$audit_execution_started_at^~^93^~^datetime^~^23^~^9$~$audit_execution_completed_at^~^93^~^datetime^~^23^~^10$~$audit_executed_from^~^12^~^varchar^~^20^~^11$~$context_type^~^12^~^varchar^~^20^~^12$~$executed_by^~^12^~^varchar^~^50^~^13$~$audit_status^~^12^~^varchar^~^7^~^14",
        "srcTrgTbllist" : [ ],
        "fileContent" : null
      }, {
        "ruleClsPropID" : 10548126,
        "paramId" : 491,
        "paramMethod" : "setDeferredSort",
        "paramValue" : "false",
        "srcTrgTbllist" : null,
        "fileContent" : null
      } ],
      "bigDataExecMode" : null,
      "srcConnServer" : null,
      "trgConnServer" : null,
      "srcConnExecMode" : null,
      "trgConnExecMode" : null,
      "thresholdFlag" : null,
      "thresholdExpression" : null
    }, {
      "classId" : 1,
      "name" : null,
      "ruleClassId" : 2266167,
      "connType" : "DATABASE",
      "execMode" : "recon",
      "index" : 0,
      "classRun" : "com.ice.bpel.GetData",
      "vid" : "GetData21",
      "classObjName" : "ICE_1583492008527",
      "queryBuilderXML" : null,
      "connId" : 2452,
      "resultType" : "a-b,b-a",
      "connName" : null,
      "connUrl" : null,
      "connFullUrl" : null,
      "sysGrpId" : 0,
      "ruleId" : 0,
      "ruleName" : null,
      "ruleParameter" : null,
      "srcTrgMaplist" : [ ],
      "exprlist" : [ ],
      "derivedexprlist" : null,
      "paramsVOLst" : [ {
        "ruleClsPropID" : 2266191,
        "paramId" : 6,
        "paramMethod" : "setQueryString",
        "paramValue" : "select * from DBO.ICE_IQA_INFO_VIEW",
        "srcTrgTbllist" : [ {
          "srcTgtColId" : 10548146,
          "ruleClsPropId" : 2266191,
          "srcTrgColName" : "flag_type",
          "srcTrgColDataType" : "varchar",
          "colFlagType" : "tgt",
          "srcTrgColVisible" : 1,
          "joinList" : null,
          "mapColName" : null,
          "colFormat" : "",
          "displayIndex" : 15
        }, {
          "srcTgtColId" : 10548147,
          "ruleClsPropId" : 2266191,
          "srcTrgColName" : "req_id",
          "srcTrgColDataType" : "int",
          "colFlagType" : "tgt",
          "srcTrgColVisible" : 1,
          "joinList" : null,
          "mapColName" : null,
          "colFormat" : "",
          "displayIndex" : 16
        }, {
          "srcTgtColId" : 10548148,
          "ruleClsPropId" : 2266191,
          "srcTrgColName" : "req_code",
          "srcTrgColDataType" : "varchar",
          "colFlagType" : "tgt",
          "srcTrgColVisible" : 1,
          "joinList" : null,
          "mapColName" : null,
          "colFormat" : "",
          "displayIndex" : 17
        }, {
          "srcTgtColId" : 10548149,
          "ruleClsPropId" : 2266191,
          "srcTrgColName" : "project_name",
          "srcTrgColDataType" : "varchar",
          "colFlagType" : "tgt",
          "srcTrgColVisible" : 1,
          "joinList" : null,
          "mapColName" : null,
          "colFormat" : "",
          "displayIndex" : 18
        }, {
          "srcTgtColId" : 10548150,
          "ruleClsPropId" : 2266191,
          "srcTrgColName" : "folder_name",
          "srcTrgColDataType" : "varchar",
          "colFlagType" : "tgt",
          "srcTrgColVisible" : 1,
          "joinList" : null,
          "mapColName" : null,
          "colFormat" : "",
          "displayIndex" : 19
        }, {
          "srcTgtColId" : 10548151,
          "ruleClsPropId" : 2266191,
          "srcTrgColName" : "req_name",
          "srcTrgColDataType" : "varchar",
          "colFlagType" : "tgt",
          "srcTrgColVisible" : 1,
          "joinList" : null,
          "mapColName" : null,
          "colFormat" : "",
          "displayIndex" : 20
        }, {
          "srcTgtColId" : 10548152,
          "ruleClsPropId" : 2266191,
          "srcTrgColName" : "req_desc",
          "srcTrgColDataType" : "varchar",
          "colFlagType" : "tgt",
          "srcTrgColVisible" : 1,
          "joinList" : null,
          "mapColName" : null,
          "colFormat" : "",
          "displayIndex" : 21
        }, {
          "srcTgtColId" : 10548153,
          "ruleClsPropId" : 2266191,
          "srcTrgColName" : "audit_exit_code",
          "srcTrgColDataType" : "float",
          "colFlagType" : "tgt",
          "srcTrgColVisible" : 1,
          "joinList" : null,
          "mapColName" : null,
          "colFormat" : "",
          "displayIndex" : 22
        }, {
          "srcTgtColId" : 10548154,
          "ruleClsPropId" : 2266191,
          "srcTrgColName" : "audit_execution_started_at",
          "srcTrgColDataType" : "datetime",
          "colFlagType" : "tgt",
          "srcTrgColVisible" : 1,
          "joinList" : null,
          "mapColName" : null,
          "colFormat" : "",
          "displayIndex" : 23
        }, {
          "srcTgtColId" : 10548155,
          "ruleClsPropId" : 2266191,
          "srcTrgColName" : "audit_execution_completed_at",
          "srcTrgColDataType" : "datetime",
          "colFlagType" : "tgt",
          "srcTrgColVisible" : 1,
          "joinList" : null,
          "mapColName" : null,
          "colFormat" : "",
          "displayIndex" : 24
        }, {
          "srcTgtColId" : 10548156,
          "ruleClsPropId" : 2266191,
          "srcTrgColName" : "audit_executed_from",
          "srcTrgColDataType" : "varchar",
          "colFlagType" : "tgt",
          "srcTrgColVisible" : 1,
          "joinList" : null,
          "mapColName" : null,
          "colFormat" : "",
          "displayIndex" : 25
        }, {
          "srcTgtColId" : 10548157,
          "ruleClsPropId" : 2266191,
          "srcTrgColName" : "context_type",
          "srcTrgColDataType" : "varchar",
          "colFlagType" : "tgt",
          "srcTrgColVisible" : 1,
          "joinList" : null,
          "mapColName" : null,
          "colFormat" : "",
          "displayIndex" : 26
        }, {
          "srcTgtColId" : 10548158,
          "ruleClsPropId" : 2266191,
          "srcTrgColName" : "executed_by",
          "srcTrgColDataType" : "varchar",
          "colFlagType" : "tgt",
          "srcTrgColVisible" : 1,
          "joinList" : null,
          "mapColName" : null,
          "colFormat" : "",
          "displayIndex" : 27
        }, {
          "srcTgtColId" : 10548159,
          "ruleClsPropId" : 2266191,
          "srcTrgColName" : "audit_status",
          "srcTrgColDataType" : "varchar",
          "colFlagType" : "tgt",
          "srcTrgColVisible" : 1,
          "joinList" : null,
          "mapColName" : null,
          "colFormat" : "",
          "displayIndex" : 28
        } ],
        "fileContent" : null
      }, {
        "ruleClsPropID" : 2266193,
        "paramId" : 16,
        "paramMethod" : "setConnId",
        "paramValue" : "2452",
        "srcTrgTbllist" : null,
        "fileContent" : null
      }, {
        "ruleClsPropID" : 2266194,
        "paramId" : 337,
        "paramMethod" : "setIsStoredProcedure",
        "paramValue" : "false",
        "srcTrgTbllist" : null,
        "fileContent" : null
      }, {
        "ruleClsPropID" : 2266195,
        "paramId" : 84,
        "paramMethod" : "setOrderByStr",
        "paramValue" : "1",
        "srcTrgTbllist" : [ ],
        "fileContent" : null
      }, {
        "ruleClsPropID" : 2266197,
        "paramId" : 82,
        "paramMethod" : "setAppendOrderBy",
        "paramValue" : "true",
        "srcTrgTbllist" : null,
        "fileContent" : null
      }, {
        "ruleClsPropID" : 2266198,
        "paramId" : 83,
        "paramMethod" : "setColumnsMInfo",
        "paramValue" : "flag_type^~^12^~^varchar^~^11^~^1$~$req_id^~^4^~^int^~^10^~^2$~$req_code^~^12^~^varchar^~^50^~^3$~$project_name^~^12^~^varchar^~^100^~^4$~$folder_name^~^12^~^varchar^~^50^~^5$~$req_name^~^12^~^varchar^~^2000^~^6$~$req_desc^~^12^~^varchar^~^4000^~^7$~$audit_exit_code^~^8^~^float^~^15^~^8$~$audit_execution_started_at^~^93^~^datetime^~^23^~^9$~$audit_execution_completed_at^~^93^~^datetime^~^23^~^10$~$audit_executed_from^~^12^~^varchar^~^20^~^11$~$context_type^~^12^~^varchar^~^20^~^12$~$executed_by^~^12^~^varchar^~^50^~^13$~$audit_status^~^12^~^varchar^~^7^~^14",
        "srcTrgTbllist" : [ ],
        "fileContent" : null
      }, {
        "ruleClsPropID" : 10548143,
        "paramId" : 491,
        "paramMethod" : "setDeferredSort",
        "paramValue" : "false",
        "srcTrgTbllist" : null,
        "fileContent" : null
      } ],
      "bigDataExecMode" : null,
      "srcConnServer" : null,
      "trgConnServer" : null,
      "srcConnExecMode" : null,
      "trgConnExecMode" : null,
      "thresholdFlag" : null,
      "thresholdExpression" : null
    } ],
    "srcTrgTbllist" : [ {
      "srcTgtColId" : 10548129,
      "ruleClsPropId" : 2266169,
      "srcTrgColName" : "flag_type",
      "srcTrgColDataType" : "varchar",
      "colFlagType" : "src",
      "srcTrgColVisible" : 1,
      "joinList" : null,
      "mapColName" : "flag_type",
      "colFormat" : "",
      "displayIndex" : 1
    }, {
      "srcTgtColId" : 10548130,
      "ruleClsPropId" : 2266169,
      "srcTrgColName" : "req_id",
      "srcTrgColDataType" : "int",
      "colFlagType" : "src",
      "srcTrgColVisible" : 1,
      "joinList" : null,
      "mapColName" : "req_id",
      "colFormat" : "",
      "displayIndex" : 2
    }, {
      "srcTgtColId" : 10548131,
      "ruleClsPropId" : 2266169,
      "srcTrgColName" : "req_code",
      "srcTrgColDataType" : "varchar",
      "colFlagType" : "src",
      "srcTrgColVisible" : 1,
      "joinList" : null,
      "mapColName" : "req_code",
      "colFormat" : "",
      "displayIndex" : 3
    }, {
      "srcTgtColId" : 10548132,
      "ruleClsPropId" : 2266169,
      "srcTrgColName" : "project_name",
      "srcTrgColDataType" : "varchar",
      "colFlagType" : "src",
      "srcTrgColVisible" : 1,
      "joinList" : null,
      "mapColName" : "project_name",
      "colFormat" : "",
      "displayIndex" : 4
    }, {
      "srcTgtColId" : 10548133,
      "ruleClsPropId" : 2266169,
      "srcTrgColName" : "folder_name",
      "srcTrgColDataType" : "varchar",
      "colFlagType" : "src",
      "srcTrgColVisible" : 1,
      "joinList" : null,
      "mapColName" : "folder_name",
      "colFormat" : "",
      "displayIndex" : 5
    }, {
      "srcTgtColId" : 10548134,
      "ruleClsPropId" : 2266169,
      "srcTrgColName" : "req_name",
      "srcTrgColDataType" : "varchar",
      "colFlagType" : "src",
      "srcTrgColVisible" : 1,
      "joinList" : null,
      "mapColName" : "req_name",
      "colFormat" : "",
      "displayIndex" : 6
    }, {
      "srcTgtColId" : 10548135,
      "ruleClsPropId" : 2266169,
      "srcTrgColName" : "req_desc",
      "srcTrgColDataType" : "varchar",
      "colFlagType" : "src",
      "srcTrgColVisible" : 1,
      "joinList" : null,
      "mapColName" : "req_desc",
      "colFormat" : "",
      "displayIndex" : 7
    }, {
      "srcTgtColId" : 10548136,
      "ruleClsPropId" : 2266169,
      "srcTrgColName" : "audit_exit_code",
      "srcTrgColDataType" : "float",
      "colFlagType" : "src",
      "srcTrgColVisible" : 1,
      "joinList" : null,
      "mapColName" : "audit_exit_code",
      "colFormat" : "",
      "displayIndex" : 8
    }, {
      "srcTgtColId" : 10548137,
      "ruleClsPropId" : 2266169,
      "srcTrgColName" : "audit_execution_started_at",
      "srcTrgColDataType" : "datetime",
      "colFlagType" : "src",
      "srcTrgColVisible" : 1,
      "joinList" : null,
      "mapColName" : "audit_execution_started_at",
      "colFormat" : "",
      "displayIndex" : 9
    }, {
      "srcTgtColId" : 10548138,
      "ruleClsPropId" : 2266169,
      "srcTrgColName" : "audit_execution_completed_at",
      "srcTrgColDataType" : "datetime",
      "colFlagType" : "src",
      "srcTrgColVisible" : 1,
      "joinList" : null,
      "mapColName" : "audit_execution_completed_at",
      "colFormat" : "",
      "displayIndex" : 10
    }, {
      "srcTgtColId" : 10548139,
      "ruleClsPropId" : 2266169,
      "srcTrgColName" : "audit_executed_from",
      "srcTrgColDataType" : "varchar",
      "colFlagType" : "src",
      "srcTrgColVisible" : 1,
      "joinList" : null,
      "mapColName" : "audit_executed_from",
      "colFormat" : "",
      "displayIndex" : 11
    }, {
      "srcTgtColId" : 10548140,
      "ruleClsPropId" : 2266169,
      "srcTrgColName" : "context_type",
      "srcTrgColDataType" : "varchar",
      "colFlagType" : "src",
      "srcTrgColVisible" : 1,
      "joinList" : null,
      "mapColName" : "context_type",
      "colFormat" : "",
      "displayIndex" : 12
    }, {
      "srcTgtColId" : 10548141,
      "ruleClsPropId" : 2266169,
      "srcTrgColName" : "executed_by",
      "srcTrgColDataType" : "varchar",
      "colFlagType" : "src",
      "srcTrgColVisible" : 1,
      "joinList" : null,
      "mapColName" : "executed_by",
      "colFormat" : "",
      "displayIndex" : 13
    }, {
      "srcTgtColId" : 10548142,
      "ruleClsPropId" : 2266169,
      "srcTrgColName" : "audit_status",
      "srcTrgColDataType" : "varchar",
      "colFlagType" : "src",
      "srcTrgColVisible" : 1,
      "joinList" : null,
      "mapColName" : "audit_status",
      "colFormat" : "",
      "displayIndex" : 14
    }, {
      "srcTgtColId" : 10548146,
      "ruleClsPropId" : 2266191,
      "srcTrgColName" : "flag_type",
      "srcTrgColDataType" : "varchar",
      "colFlagType" : "tgt",
      "srcTrgColVisible" : 1,
      "joinList" : null,
      "mapColName" : "flag_type",
      "colFormat" : "",
      "displayIndex" : 15
    }, {
      "srcTgtColId" : 10548147,
      "ruleClsPropId" : 2266191,
      "srcTrgColName" : "req_id",
      "srcTrgColDataType" : "int",
      "colFlagType" : "tgt",
      "srcTrgColVisible" : 1,
      "joinList" : null,
      "mapColName" : "req_id",
      "colFormat" : "",
      "displayIndex" : 16
    }, {
      "srcTgtColId" : 10548148,
      "ruleClsPropId" : 2266191,
      "srcTrgColName" : "req_code",
      "srcTrgColDataType" : "varchar",
      "colFlagType" : "tgt",
      "srcTrgColVisible" : 1,
      "joinList" : null,
      "mapColName" : "req_code",
      "colFormat" : "",
      "displayIndex" : 17
    }, {
      "srcTgtColId" : 10548149,
      "ruleClsPropId" : 2266191,
      "srcTrgColName" : "project_name",
      "srcTrgColDataType" : "varchar",
      "colFlagType" : "tgt",
      "srcTrgColVisible" : 1,
      "joinList" : null,
      "mapColName" : "project_name",
      "colFormat" : "",
      "displayIndex" : 18
    }, {
      "srcTgtColId" : 10548150,
      "ruleClsPropId" : 2266191,
      "srcTrgColName" : "folder_name",
      "srcTrgColDataType" : "varchar",
      "colFlagType" : "tgt",
      "srcTrgColVisible" : 1,
      "joinList" : null,
      "mapColName" : "folder_name",
      "colFormat" : "",
      "displayIndex" : 19
    }, {
      "srcTgtColId" : 10548151,
      "ruleClsPropId" : 2266191,
      "srcTrgColName" : "req_name",
      "srcTrgColDataType" : "varchar",
      "colFlagType" : "tgt",
      "srcTrgColVisible" : 1,
      "joinList" : null,
      "mapColName" : "req_name",
      "colFormat" : "",
      "displayIndex" : 20
    }, {
      "srcTgtColId" : 10548152,
      "ruleClsPropId" : 2266191,
      "srcTrgColName" : "req_desc",
      "srcTrgColDataType" : "varchar",
      "colFlagType" : "tgt",
      "srcTrgColVisible" : 1,
      "joinList" : null,
      "mapColName" : "req_desc",
      "colFormat" : "",
      "displayIndex" : 21
    }, {
      "srcTgtColId" : 10548153,
      "ruleClsPropId" : 2266191,
      "srcTrgColName" : "audit_exit_code",
      "srcTrgColDataType" : "float",
      "colFlagType" : "tgt",
      "srcTrgColVisible" : 1,
      "joinList" : null,
      "mapColName" : "audit_exit_code",
      "colFormat" : "",
      "displayIndex" : 22
    }, {
      "srcTgtColId" : 10548154,
      "ruleClsPropId" : 2266191,
      "srcTrgColName" : "audit_execution_started_at",
      "srcTrgColDataType" : "datetime",
      "colFlagType" : "tgt",
      "srcTrgColVisible" : 1,
      "joinList" : null,
      "mapColName" : "audit_execution_started_at",
      "colFormat" : "",
      "displayIndex" : 23
    }, {
      "srcTgtColId" : 10548155,
      "ruleClsPropId" : 2266191,
      "srcTrgColName" : "audit_execution_completed_at",
      "srcTrgColDataType" : "datetime",
      "colFlagType" : "tgt",
      "srcTrgColVisible" : 1,
      "joinList" : null,
      "mapColName" : "audit_execution_completed_at",
      "colFormat" : "",
      "displayIndex" : 24
    }, {
      "srcTgtColId" : 10548156,
      "ruleClsPropId" : 2266191,
      "srcTrgColName" : "audit_executed_from",
      "srcTrgColDataType" : "varchar",
      "colFlagType" : "tgt",
      "srcTrgColVisible" : 1,
      "joinList" : null,
      "mapColName" : "audit_executed_from",
      "colFormat" : "",
      "displayIndex" : 25
    }, {
      "srcTgtColId" : 10548157,
      "ruleClsPropId" : 2266191,
      "srcTrgColName" : "context_type",
      "srcTrgColDataType" : "varchar",
      "colFlagType" : "tgt",
      "srcTrgColVisible" : 1,
      "joinList" : null,
      "mapColName" : "context_type",
      "colFormat" : "",
      "displayIndex" : 26
    }, {
      "srcTgtColId" : 10548158,
      "ruleClsPropId" : 2266191,
      "srcTrgColName" : "executed_by",
      "srcTrgColDataType" : "varchar",
      "colFlagType" : "tgt",
      "srcTrgColVisible" : 1,
      "joinList" : null,
      "mapColName" : "executed_by",
      "colFormat" : "",
      "displayIndex" : 27
    }, {
      "srcTgtColId" : 10548159,
      "ruleClsPropId" : 2266191,
      "srcTrgColName" : "audit_status",
      "srcTrgColDataType" : "varchar",
      "colFlagType" : "tgt",
      "srcTrgColVisible" : 1,
      "joinList" : null,
      "mapColName" : "audit_status",
      "colFormat" : "",
      "displayIndex" : 28
    } ],
    "colMapList" : [ {
      "colMapId" : 10548162,
      "srcColId" : 10548129,
      "trgColId" : 10548146,
      "colMapType" : "join",
      "srcColName" : "flag_type",
      "tgtColName" : "flag_type",
      "colMapExpr" : "flag_type=flag_type",
      "srcTrgColMapVisible" : 1,
      "displayIndex" : 30
    } ],
    "objectVOList" : null,
    "srcCount" : null,
    "trgCount" : null,
    "srcMissing" : null,
    "trgMissing" : null,
    "commonRows" : null,
    "classResult" : null,
    "classStatus" : null,
    "resultType" : null,
    "showErrorData" : null,
    "reportXlsx" : null,
    "ruleParameter" : "",
    "classCreatedBy" : 0,
    "classModifydBy" : 0,
    "classCreateDate" : null,
    "classModifyDate" : null,
    "exprVOList" : [ {
      "exprID" : 2266226,
      "exprLogID" : 0,
      "exprName" : "audit_executed_from",
      "expression" : "S.audit_executed_from == T.audit_executed_from",
      "result" : "Pass",
      "exprType" : "5",
      "exprVisible" : 1,
      "exprIndex" : 29,
      "ruleId" : 2266165,
      "ruleInstanceId" : 0,
      "ruleClassId" : 2266168,
      "ruleName" : null,
      "trueCount" : null,
      "falseCount" : null,
      "errCount" : null,
      "exprOrg" : null,
      "tc" : null,
      "fc" : null,
      "er" : null,
      "name" : null,
      "ve" : 0,
      "exporg" : null
    } ],
    "derivedvariablelist" : null
  }
}